PythonJichujiaochengCYuyanZhongwenwang/README.md
PythonJichujiaochengCYuyanZhongwenwang/__init__.py
PythonJichujiaochengCYuyanZhongwenwang/__main__.py
PythonJichujiaochengCYuyanZhongwenwang/file.epub
PythonJichujiaochengCYuyanZhongwenwang/index.html
PythonJichujiaochengCYuyanZhongwenwang/css/__init__.py
PythonJichujiaochengCYuyanZhongwenwang/css/annotations.css
PythonJichujiaochengCYuyanZhongwenwang/css/main.css
PythonJichujiaochengCYuyanZhongwenwang/css/normalize.css
PythonJichujiaochengCYuyanZhongwenwang/css/popup.css
PythonJichujiaochengCYuyanZhongwenwang/font/__init__.py
PythonJichujiaochengCYuyanZhongwenwang/font/fontello.eot
PythonJichujiaochengCYuyanZhongwenwang/font/fontello.svg
PythonJichujiaochengCYuyanZhongwenwang/font/fontello.ttf
PythonJichujiaochengCYuyanZhongwenwang/font/fontello.woff
PythonJichujiaochengCYuyanZhongwenwang/img/__init__.py
PythonJichujiaochengCYuyanZhongwenwang/img/annotator-glyph-sprite.png
PythonJichujiaochengCYuyanZhongwenwang/img/annotator-icon-sprite.png
PythonJichujiaochengCYuyanZhongwenwang/img/apple-touch-icon.png
PythonJichujiaochengCYuyanZhongwenwang/img/cancelfullscreen.png
PythonJichujiaochengCYuyanZhongwenwang/img/close.png
PythonJichujiaochengCYuyanZhongwenwang/img/fullscreen.png
PythonJichujiaochengCYuyanZhongwenwang/img/loader.gif
PythonJichujiaochengCYuyanZhongwenwang/img/menu-icon.png
PythonJichujiaochengCYuyanZhongwenwang/img/save.png
PythonJichujiaochengCYuyanZhongwenwang/img/saved.png
PythonJichujiaochengCYuyanZhongwenwang/img/settings-s.png
PythonJichujiaochengCYuyanZhongwenwang/img/settings.png
PythonJichujiaochengCYuyanZhongwenwang/img/star.png
PythonJichujiaochengCYuyanZhongwenwang/js/__init__.py
PythonJichujiaochengCYuyanZhongwenwang/js/epub.js
PythonJichujiaochengCYuyanZhongwenwang/js/epub.min.js
PythonJichujiaochengCYuyanZhongwenwang/js/epub.min.map
PythonJichujiaochengCYuyanZhongwenwang/js/hooks.min.js
PythonJichujiaochengCYuyanZhongwenwang/js/hooks.min.map
python_jichujiaocheng_c_yuyan_zhongwenwang-2024.3.4.0.dist-info/METADATA
python_jichujiaocheng_c_yuyan_zhongwenwang-2024.3.4.0.dist-info/WHEEL
python_jichujiaocheng_c_yuyan_zhongwenwang-2024.3.4.0.dist-info/entry_points.txt
python_jichujiaocheng_c_yuyan_zhongwenwang-2024.3.4.0.dist-info/top_level.txt
python_jichujiaocheng_c_yuyan_zhongwenwang-2024.3.4.0.dist-info/RECORD
